dizzyblog/__init__.py
dizzyblog/main.py
dizzyblog-0.2.0.dist-info/METADATA
dizzyblog-0.2.0.dist-info/WHEEL
dizzyblog-0.2.0.dist-info/entry_points.txt
dizzyblog-0.2.0.dist-info/top_level.txt
dizzyblog-0.2.0.dist-info/RECORD
