Metadata-Version: 2.1
Name: dizzyblog
Version: 0.2.0
Summary: A simple blogging CLI application.
Home-page: https://github.com/yourusername/dizzyblog
Author: Your Name
Author-email: your_email@example.com
Classifier: Programming Language :: Python :: 3
Classifier: License :: OSI Approved :: MIT License
Classifier: Operating System :: OS Independent
Requires-Python: >=3.6
